Metadata-Version: 2.1
Name: scylla-for-docker
Version: 0.0.2
Summary: Spin up docker containers for easy in-line testing
Home-page: https://github.com/talosiot/scylla-for-docker/tree/master/
Author: Will Gathright
Author-email: wgathright@talosiot.com
License: Apache Software License 2.0
Keywords: talosiot
Platform: UNKNOWN
Classifier: Development Status :: 3 - Alpha
Classifier: Intended Audience :: Developers
Classifier: License :: OSI Approved :: Apache Software License
Classifier: Natural Language :: English
Classifier: Programming Language :: Python :: 3.6
Classifier: Programming Language :: Python :: 3.7
Classifier: Programming Language :: Python :: 3.8
Requires-Python: >=3.6
License-File: LICENSE
